pineko/__init__.py
pineko/check.py
pineko/cli/__init__.py
pineko/cli/_base.py
pineko/cli/check.py
pineko/cli/compare.py
pineko/cli/convolve.py
pineko/cli/fonll.py
pineko/cli/gen_sv.py
pineko/cli/kfactor.py
pineko/cli/opcard.py
pineko/cli/scaffold.py
pineko/cli/theory_.py
pineko/comparator.py
pineko/configs.py
pineko/evolve.py
pineko/fonll.py
pineko/kfactor.py
pineko/parser.py
pineko/scaffold.py
pineko/scale_variations.py
pineko/theory.py
pineko/theory_card.py
pineko/utils.py
pineko/version.py
pineko-0.5.0.dist-info/LICENSE
pineko-0.5.0.dist-info/METADATA
pineko-0.5.0.dist-info/WHEEL
pineko-0.5.0.dist-info/entry_points.txt
pineko-0.5.0.dist-info/RECORD
