Metadata-Version: 2.3
Name: pineko
Version: 0.5.0
Summary: Combine PineAPPL grids and EKOs into FK tables
Author: Alessandro Candido
Author-email: alessandro.candido@mi.infn.it
Requires-Python: >=3.9,<3.13
Classifier: License :: OSI Approved :: GNU General Public License v3 (GPLv3)
Classifier: Programming Language :: Python
Classifier: Programming Language :: Python :: 3
Classifier: Programming Language :: Python :: 3.9
Classifier: Programming Language :: Python :: 3.10
Classifier: Programming Language :: Python :: 3.11
Classifier: Programming Language :: Python :: 3.12
Classifier: Topic :: Scientific/Engineering
Classifier: Topic :: Scientific/Engineering :: Physics
Provides-Extra: docs
Provides-Extra: nnpdf
Requires-Dist: PyYAML (>=6.0,<7.0)
Requires-Dist: click (>=8.0.4,<9.0.0)
Requires-Dist: eko (>=0.15.0,<0.16.0)
Requires-Dist: nnpdf-data (>=0.0.3) ; extra == "nnpdf"
Requires-Dist: numpy (>=1.21.0,<2.0.0)
Requires-Dist: pandas (>=2.1,<3.0)
Requires-Dist: pineappl (>=1.0.0,<2.0.0)
Requires-Dist: rich (>=12.5.1,<13.0.0)
Requires-Dist: rich-click (>=1.8.4,<2.0.0)
Requires-Dist: tomli (>=2.0.1,<3.0.0)
Project-URL: Repository, https://github.com/N3PDF/pineko
